myelin_morphometrics/__init__.py
napari_cci_annotator/__init__.py
napari_cci_annotator/_annotations_handler.py
napari_cci_annotator/_backend_detect.py
napari_cci_annotator/_config.py
napari_cci_annotator/_id_table.py
napari_cci_annotator/_image_handler.py
napari_cci_annotator/_reader.py
napari_cci_annotator/_sample_data.py
napari_cci_annotator/_settigns.py
napari_cci_annotator/_widget.py
napari_cci_annotator/_writer.py
napari_cci_annotator/morphometrics.py
napari_cci_annotator/napari.yaml
napari_cci_annotator/segment_large_image_using_yolo.py
napari_cci_annotator/_tests/__init__.py
napari_cci_annotator/_tests/test_reader.py
napari_cci_annotator/_tests/test_sample_data.py
napari_cci_annotator/_tests/test_widget.py
napari_cci_annotator/_tests/test_writer.py
napari_cci_annotator-0.7.1.dist-info/METADATA
napari_cci_annotator-0.7.1.dist-info/WHEEL
napari_cci_annotator-0.7.1.dist-info/entry_points.txt
napari_cci_annotator-0.7.1.dist-info/top_level.txt
napari_cci_annotator-0.7.1.dist-info/RECORD
